{"valid_AphiaID": 420581, "valid_name": "Costasiella ocellifera", "lsid": "urn:lsid:marinespecies.org:taxname:420581", "match_type": "exact", "rank": "Species", "isFreshwater": null, "valid_authority": "(Simroth, 1895)", "kingdom": "Animalia", "class": "Gastropoda", "AphiaID": 420581, "isMarine": 1, "family": "Costasiellidae", "scientificname": "Costasiella ocellifera", "modified": "2011-10-03T22:55:39Z", "phylum": "Mollusca", "status": "accepted", "unacceptreason": null, "authority": "(Simroth, 1895)", "isBrackish": null, "isTerrestrial": null, "order": "Sacoglossa", "url": "http://www.marinespecies.org/aphia.php?p=taxdetails&id=420581", "genus": "Costasiella", "citation": "Rosenberg, G. (2011). Costasiella ocellifera (Simroth, 1895). In:  MolluscaBase (2017). Accessed through:  World Register of Marine Species at http://www.marinespecies.org/aphia.php?p=taxdetails&id=420581 on 2017-12-10", "isExtinct": null}