{"valid_AphiaID": 715645, "valid_name": "Phanerophthalmus olivaceus", "lsid": "urn:lsid:marinespecies.org:taxname:715646", "match_type": "exact", "rank": "Species", "isFreshwater": null, "valid_authority": "(Ehrenberg, 1828)", "kingdom": "Animalia", "class": "Gastropoda", "AphiaID": 715646, "isMarine": 1, "family": "Haminoeidae", "scientificname": "Cryptophthalmus olivaceus", "modified": "2013-01-15T08:35:55Z", "phylum": "Mollusca", "status": "unaccepted", "unacceptreason": "original combination", "authority": "Ehrenberg, 1828", "isBrackish": null, "isTerrestrial": null, "order": "Cephalaspidea", "url": "http://www.marinespecies.org/aphia.php?p=taxdetails&id=715646", "genus": "Cryptophthalmus", "citation": "Bouchet, P. (2013). Cryptophthalmus olivaceus Ehrenberg, 1828. In:  MolluscaBase (2017). Accessed through:  World Register of Marine Species at http://www.marinespecies.org/aphia.php?p=taxdetails&id=715646 on 2017-12-10", "isExtinct": null}