{"isExtinct": null, "authority": "Er. Marcus & Ev. Marcus, 1970", "valid_name": "Ercolania coerulea", "isMarine": 1, "isTerrestrial": null, "AphiaID": 605632, "citation": "Bouchet, P. (2012). Stiliger cricetus Er. Marcus & Ev. Marcus, 1970. In:  MolluscaBase (2017). Accessed through:  World Register of Marine Species at http://www.marinespecies.org/aphia.php?p=taxdetails&id=605632 on 2017-12-11", "class": "Gastropoda", "modified": "2012-07-13T10:42:50Z", "phylum": "Mollusca", "valid_authority": "Trinchese, 1892", "url": "http://www.marinespecies.org/aphia.php?p=taxdetails&id=605632", "unacceptreason": null, "order": "Sacoglossa", "isBrackish": null, "kingdom": "Animalia", "genus": "Stiliger", "valid_AphiaID": 141560, "lsid": "urn:lsid:marinespecies.org:taxname:605632", "status": "unaccepted", "rank": "Species", "isFreshwater": null, "scientificname": "Stiliger cricetus", "match_type": "exact", "family": "Limapontiidae"}