{"family": "Chromodorididae", "url": "http://www.marinespecies.org/aphia.php?p=taxdetails&id=558351", "isBrackish": null, "order": "Nudibranchia", "unacceptreason": null, "isTerrestrial": 0, "kingdom": "Animalia", "match_type": "exact", "isMarine": 1, "authority": "Bergh, 1905", "phylum": "Mollusca", "lsid": "urn:lsid:marinespecies.org:taxname:558351", "valid_authority": "Bergh, 1905", "status": "accepted", "valid_name": "Chromodoris bimaensis", "genus": "Chromodoris", "isExtinct": null, "valid_AphiaID": 558351, "class": "Gastropoda", "AphiaID": 558351, "isFreshwater": 0, "modified": "2011-01-14T10:21:57Z", "rank": "Species", "citation": "Caballer, M. (2011). Chromodoris bimaensis Bergh, 1905. In:  MolluscaBase (2017). Accessed through:  World Register of Marine Species at http://marinespecies.org/aphia.php?p=taxdetails&id=558351 on 2017-12-10", "scientificname": "Chromodoris bimaensis"}