{"family": "Limacinidae", "url": "http://www.marinespecies.org/aphia.php?p=taxdetails&id=724910", "isBrackish": null, "order": "Thecosomata", "unacceptreason": null, "isTerrestrial": null, "kingdom": "Animalia", "match_type": "exact", "isMarine": 1, "authority": "(d'Orbigny, 1834)", "phylum": "Mollusca", "lsid": "urn:lsid:marinespecies.org:taxname:724910", "valid_authority": "(d'Orbigny, 1834)", "status": "unaccepted", "valid_name": "Heliconoides inflatus", "genus": "Embolus", "isExtinct": null, "valid_AphiaID": 605965, "class": "Gastropoda", "AphiaID": 724910, "isFreshwater": null, "modified": "2013-04-15T08:48:38Z", "rank": "Species", "citation": "Bouchet, P. (2013). Embolus inflatus (d'Orbigny, 1834). In:  MolluscaBase (2017). Accessed through:  World Register of Marine Species at http://www.marinespecies.org/aphia.php?p=taxdetails&id=724910 on 2017-12-10", "scientificname": "Embolus inflatus"}