{"isExtinct": null, "authority": "Gosliner & Kuzirian, 1990", "valid_name": "Coryphellina marcusorum", "isMarine": 1, "isTerrestrial": null, "AphiaID": 224326, "citation": "Picton, B.; Bouchet, P. (2017). Flabellina marcusorum Gosliner & Kuzirian, 1990. In:  MolluscaBase (2017). Accessed through:  World Register of Marine Species at http://www.marinespecies.org/aphia.php?p=taxdetails&id=224326 on 2017-12-11", "class": "Gastropoda", "modified": "2017-12-02T18:26:38Z", "phylum": "Mollusca", "valid_authority": "(Gosliner & Kuzirian, 1990)", "url": "http://www.marinespecies.org/aphia.php?p=taxdetails&id=224326", "unacceptreason": null, "order": "Nudibranchia", "isBrackish": null, "kingdom": "Animalia", "genus": "Flabellina", "valid_AphiaID": 1047497, "lsid": "urn:lsid:marinespecies.org:taxname:224326", "status": "unaccepted", "rank": "Species", "isFreshwater": null, "scientificname": "Flabellina marcusorum", "match_type": "exact", "family": "Flabellinidae"}