{"valid_AphiaID": 137750, "valid_name": "Cavolinia", "lsid": "urn:lsid:marinespecies.org:taxname:741747", "match_type": "exact", "rank": "Genus", "isFreshwater": null, "valid_authority": "Abildgaard, 1791", "kingdom": "Animalia", "class": "Gastropoda", "AphiaID": 741747, "isMarine": 1, "family": "Cavoliniidae", "scientificname": "Archonta", "modified": "2013-09-24T22:58:49Z", "phylum": "Mollusca", "status": "nomen dubium", "unacceptreason": null, "authority": "Montfort, 1810", "isBrackish": null, "isTerrestrial": null, "order": "Thecosomata", "url": "http://www.marinespecies.org/aphia.php?p=taxdetails&id=741747", "genus": "Archonta", "citation": "Gofas, S. (2013). Archonta Montfort, 1810. In:  MolluscaBase (2017). Accessed through:  World Register of Marine Species at http://marinespecies.org/aphia.php?p=taxdetails&id=741747 on 2017-12-10", "isExtinct": null}