{"isExtinct": null, "authority": "[sic]", "valid_name": "Gastropteron", "isMarine": 1, "isTerrestrial": null, "AphiaID": 138031, "citation": "Gofas, S. (2017). Gasteropteron [sic]. In:  MolluscaBase (2017). Accessed through:  World Register of Marine Species at http://www.marinespecies.org/aphia.php?p=taxdetails&id=138031 on 2017-12-10", "class": "Gastropoda", "modified": "2013-10-04T06:45:00Z", "phylum": "Mollusca", "valid_authority": "Kosse, 1813", "url": "http://www.marinespecies.org/aphia.php?p=taxdetails&id=138031", "unacceptreason": "incorrect subsequent spelling [by Schweigger, 1820] of <i>Gastropteron</i> Kosse, 1813", "order": "Cephalaspidea", "isBrackish": null, "kingdom": "Animalia", "genus": "Gasteropteron", "valid_AphiaID": 181211, "lsid": "urn:lsid:marinespecies.org:taxname:138031", "status": "unaccepted", "rank": "Genus", "isFreshwater": null, "scientificname": "Gasteropteron", "match_type": "exact", "family": "Gasteropteridae"}