{"isExtinct": null, "authority": "Pfeffer in Martens & Pfeffer, 1886", "valid_name": "Cuthona georgiana", "isMarine": 1, "isTerrestrial": null, "AphiaID": 536867, "citation": "Bouchet, P. (2010). Aeolis georgiana Pfeffer in Martens & Pfeffer, 1886. In:  MolluscaBase (2017). Accessed through:  World Register of Marine Species at http://www.marinespecies.org/traits/aphia.php?p=taxdetails&id=536867 on 2017-12-11", "class": "Gastropoda", "modified": "2010-11-04T20:13:59Z", "phylum": "Mollusca", "valid_authority": "(Pfeffer in Martens & Pfeffer, 1886)", "url": "http://www.marinespecies.org/aphia.php?p=taxdetails&id=536867", "unacceptreason": "original combination", "order": "Nudibranchia", "isBrackish": null, "kingdom": "Animalia", "genus": "Aeolis", "valid_AphiaID": 197125, "lsid": "urn:lsid:marinespecies.org:taxname:536867", "status": "unaccepted", "rank": "Species", "isFreshwater": null, "scientificname": "Aeolis georgiana", "match_type": "exact", "family": "Aeolidiidae"}