{"valid_AphiaID": 224463, "valid_name": "Thliptodon diaphanus", "lsid": "urn:lsid:marinespecies.org:taxname:829383", "match_type": "exact", "rank": "Species", "isFreshwater": null, "valid_authority": "(Meisenheimer, 1902)", "kingdom": "Animalia", "class": "Gastropoda", "AphiaID": 829383, "isMarine": 1, "family": "Thliptodontidae", "scientificname": "Pteroceanis diaphana", "modified": "2015-01-19T20:39:50Z", "phylum": "Mollusca", "status": "unaccepted", "unacceptreason": "original combination", "authority": "Meisenheimer, 1902", "isBrackish": null, "isTerrestrial": null, "order": "Gymnosomata", "url": "http://www.marinespecies.org/aphia.php?p=taxdetails&id=829383", "genus": "Pteroceanis", "citation": "Bouchet, P. (2015). Pteroceanis diaphana Meisenheimer, 1902. In:  MolluscaBase (2017). Accessed through:  World Register of Marine Species at http://www.marinespecies.org/aphia.php?p=taxdetails&id=829383 on 2017-12-10", "isExtinct": null}