{"isExtinct": null, "authority": "DaCosta, Padula & Schr\u00f6dl, 2010", "valid_name": "Felimare juliae", "isMarine": 1, "isTerrestrial": null, "AphiaID": 531102, "citation": "Bouchet, P. (2012). Hypselodoris juliae DaCosta, Padula & Schr\u00f6dl, 2010. In:  MolluscaBase (2017). Accessed through:  World Register of Marine Species at http://www.marinespecies.org/aphia.php?p=taxdetails&id=531102 on 2017-12-11", "class": "Gastropoda", "modified": "2012-05-18T14:51:53Z", "phylum": "Mollusca", "valid_authority": "(DaCosta, Padula & Schr\u00f6dl, 2010)", "url": "http://www.marinespecies.org/aphia.php?p=taxdetails&id=531102", "unacceptreason": "original combination", "order": "Nudibranchia", "isBrackish": null, "kingdom": "Animalia", "genus": "Hypselodoris", "valid_AphiaID": 597826, "lsid": "urn:lsid:marinespecies.org:taxname:531102", "status": "unaccepted", "rank": "Species", "isFreshwater": null, "scientificname": "Hypselodoris juliae", "match_type": "exact", "family": "Chromodorididae"}