{"family": "Dorididae", "url": "http://www.marinespecies.org/aphia.php?p=taxdetails&id=890438", "isBrackish": null, "order": "Nudibranchia", "unacceptreason": "invalid: secondary junior homonym of <i>Doris maculata</i> Garstang, 1896; <i>Doris odonoghuei</i> is a replacement name", "isTerrestrial": null, "kingdom": "Animalia", "match_type": "exact", "isMarine": 1, "authority": "O'Donoghue, 1926", "phylum": "Mollusca", "lsid": "urn:lsid:marinespecies.org:taxname:890438", "valid_authority": "(Steinberg, 1963)", "status": "unaccepted", "valid_name": "Diaulula odonoghuei", "genus": "Doridigitata", "isExtinct": null, "valid_AphiaID": 890436, "class": "Gastropoda", "AphiaID": 890438, "isFreshwater": null, "modified": "2016-12-14T00:43:35Z", "rank": "Species", "citation": "Bouchet, P. (2016). Doridigitata maculata O'Donoghue, 1926. In:  MolluscaBase (2017). Accessed through:  World Register of Marine Species at http://www.marinespecies.org/aphia.php?p=taxdetails&id=890438 on 2017-12-10", "scientificname": "Doridigitata maculata"}