{"valid_AphiaID": 827683, "valid_name": "Cylindrobulla schuppi", "lsid": "urn:lsid:marinespecies.org:taxname:827683", "match_type": "exact", "rank": "Species", "isFreshwater": null, "valid_authority": "Laetz, Christa, H\u00e4ndeler & W\u00e4gele, 2014", "kingdom": "Animalia", "class": "Gastropoda", "AphiaID": 827683, "isMarine": 1, "family": "Cylindrobullidae", "scientificname": "Cylindrobulla schuppi", "modified": "2014-12-15T19:56:54Z", "phylum": "Mollusca", "status": "accepted", "unacceptreason": null, "authority": "Laetz, Christa, H\u00e4ndeler & W\u00e4gele, 2014", "isBrackish": null, "isTerrestrial": null, "order": "Sacoglossa", "url": "http://www.marinespecies.org/aphia.php?p=taxdetails&id=827683", "genus": "Cylindrobulla", "citation": "Bouchet, P. (2014). Cylindrobulla schuppi Laetz, Christa, H\u00e4ndeler & W\u00e4gele, 2014. In:  MolluscaBase (2017). Accessed through:  World Register of Marine Species at http://www.marinespecies.org/aphia.php?p=taxdetails&id=827683 on 2017-12-10", "isExtinct": null}