{"isExtinct": 0, "authority": "(Gmelin, 1791)", "valid_name": "Akera soluta", "isMarine": 1, "isTerrestrial": null, "AphiaID": 217247, "citation": "Marshall, B.; Rosenberg, G. (2015). Akera soluta (Gmelin, 1791). In:  MolluscaBase (2017). Accessed through:  World Register of Marine Species at http://marinespecies.org/aphia.php/aphia.php?p=taxdetails&id=217247 on 2017-12-10", "class": "Gastropoda", "modified": "2015-01-16T11:00:55Z", "phylum": "Mollusca", "valid_authority": "(Gmelin, 1791)", "url": "http://www.marinespecies.org/aphia.php?p=taxdetails&id=217247", "unacceptreason": null, "order": "Anaspidea", "isBrackish": null, "kingdom": "Animalia", "genus": "Akera", "valid_AphiaID": 217247, "lsid": "urn:lsid:marinespecies.org:taxname:217247", "status": "accepted", "rank": "Species", "isFreshwater": null, "scientificname": "Akera soluta", "match_type": "exact", "family": "Akeridae"}