{"family": "Plakobranchidae", "url": "http://www.marinespecies.org/aphia.php?p=taxdetails&id=494480", "isBrackish": null, "order": "Sacoglossa", "unacceptreason": null, "isTerrestrial": null, "kingdom": "Animalia", "match_type": "exact", "isMarine": 1, "authority": "Ev. Marcus & Er. Marcus, 1970", "phylum": "Mollusca", "lsid": "urn:lsid:marinespecies.org:taxname:494480", "valid_authority": "Ev. Marcus & Er. Marcus, 1970", "status": "accepted", "valid_name": "Elysia vreelandae", "genus": "Elysia", "isExtinct": null, "valid_AphiaID": 494480, "class": "Gastropoda", "AphiaID": 494480, "isFreshwater": null, "modified": "2016-03-30T10:52:05Z", "rank": "Species", "citation": "Bouchet, P. (2016). Elysia vreelandae Ev. Marcus & Er. Marcus, 1970. In:  MolluscaBase (2017). Accessed through:  World Register of Marine Species at http://www.marinespecies.org/aphia.php?p=taxdetails&id=494480 on 2017-12-10", "scientificname": "Elysia vreelandae"}