{"isExtinct": null, "authority": "Dunker, 1853", "valid_name": "Bulla striata", "isMarine": 1, "isTerrestrial": null, "AphiaID": 574801, "citation": "Bouchet, P. (2011). Bulla adansonii var. minor Dunker, 1853. In:  MolluscaBase (2017). Accessed through:  World Register of Marine Species at http://www.marinespecies.org/traits/aphia.php?p=taxdetails&id=574801 on 2017-12-10", "class": "Gastropoda", "modified": "2011-07-02T11:54:04Z", "phylum": "Mollusca", "valid_authority": "Brugui\u00e8re, 1792", "url": "http://www.marinespecies.org/aphia.php?p=taxdetails&id=574801", "unacceptreason": null, "order": "Cephalaspidea", "isBrackish": null, "kingdom": "Animalia", "genus": "Bulla", "valid_AphiaID": 138940, "lsid": "urn:lsid:marinespecies.org:taxname:574801", "status": "unaccepted", "rank": "Variety", "isFreshwater": null, "scientificname": "Bulla adansonii var. minor", "match_type": "exact", "family": "Bullidae"}