{"family": "Dorididae", "url": "http://www.marinespecies.org/aphia.php?p=taxdetails&id=748469", "isBrackish": null, "order": "Nudibranchia", "unacceptreason": "synonym", "isTerrestrial": null, "kingdom": "Animalia", "match_type": "exact", "isMarine": 1, "authority": "Thompson W., 1840", "phylum": "Mollusca", "lsid": "urn:lsid:marinespecies.org:taxname:748469", "valid_authority": "(Montagu, 1808)", "status": "unaccepted", "valid_name": "Goniodoris nodosa", "genus": "Doris", "isExtinct": null, "valid_AphiaID": 140033, "class": "Gastropoda", "AphiaID": 748469, "isFreshwater": null, "modified": "2014-01-30T13:11:24Z", "rank": "Species", "citation": "Gofas, S. (2014). Doris elongata Thompson W., 1840. In:  MolluscaBase (2017). Accessed through:  World Register of Marine Species at http://www.marinespecies.org/traits/aphia.php?p=taxdetails&id=748469 on 2017-12-10", "scientificname": "Doris elongata"}