{"family": "Tritoniidae", "url": "http://www.marinespecies.org/aphia.php?p=taxdetails&id=141732", "isBrackish": null, "order": "Nudibranchia", "unacceptreason": null, "isTerrestrial": null, "kingdom": "Animalia", "match_type": "exact", "isMarine": 1, "authority": "Odhner, 1922", "phylum": "Mollusca", "lsid": "urn:lsid:marinespecies.org:taxname:141732", "valid_authority": "Odhner, 1922", "status": "accepted", "valid_name": "Tritonia griegi", "genus": "Tritonia", "isExtinct": null, "valid_AphiaID": 141732, "class": "Gastropoda", "AphiaID": 141732, "isFreshwater": null, "modified": "2004-12-21T16:54:05Z", "rank": "Species", "citation": "Gofas, S. (2004). Tritonia griegi Odhner, 1922. In:  MolluscaBase (2017). Accessed through:  World Register of Marine Species at http://www.marinespecies.org/aphia.php?p=taxdetails&id=141732 on 2017-12-10", "scientificname": "Tritonia griegi"}