{"valid_AphiaID": 172, "valid_name": "Aplysiidae", "lsid": "urn:lsid:marinespecies.org:taxname:411924", "match_type": "exact", "rank": null, "isFreshwater": null, "valid_authority": "Lamarck, 1809", "kingdom": null, "class": null, "AphiaID": 411924, "isMarine": 1, "family": null, "scientificname": "Aplysiinae", "modified": "2016-03-26T13:45:31Z", "phylum": null, "status": "alternate representation", "unacceptreason": null, "authority": "Lamarck, 1809", "isBrackish": null, "isTerrestrial": null, "order": null, "url": "http://www.marinespecies.org/aphia.php?p=taxdetails&id=411924", "genus": null, "citation": "Bouchet, P. (2016). Aplysiinae Lamarck, 1809. In:  MolluscaBase (2017). Accessed through:  World Register of Marine Species at http://marinespecies.org/aphia.php?p=taxdetails&id=411924 on 2017-12-10", "isExtinct": null}