{"isExtinct": null, "authority": "Linnaeus, 1758", "valid_name": "Physa fontinalis", "isMarine": 1, "isTerrestrial": null, "AphiaID": 591666, "citation": "Bouchet, P. (2011). Bulla fontinalis Linnaeus, 1758. In:  MolluscaBase (2017). Accessed through:  World Register of Marine Species at http://www.marinespecies.org/aphia.php?p=taxdetails&id=591666 on 2017-12-10", "class": "Gastropoda", "modified": "2011-12-24T20:17:31Z", "phylum": "Mollusca", "valid_authority": "(Linnaeus, 1758)", "url": "http://www.marinespecies.org/aphia.php?p=taxdetails&id=591666", "unacceptreason": "original combination", "order": "Cephalaspidea", "isBrackish": null, "kingdom": "Animalia", "genus": "Bulla", "valid_AphiaID": 248248, "lsid": "urn:lsid:marinespecies.org:taxname:591666", "status": "unaccepted", "rank": "Species", "isFreshwater": null, "scientificname": "Bulla fontinalis", "match_type": "exact", "family": "Bullidae"}