{"isExtinct": null, "authority": "Montrouzier, 1861", "valid_name": "Volvatella vigourouxi", "isMarine": 1, "isTerrestrial": null, "AphiaID": 754452, "citation": "Bouchet, P. (2014). Lophocercus vigourouxi. In:  MolluscaBase (2017). Accessed through:  World Register of Marine Species at http://www.marinespecies.org/aphia.php?p=taxdetails&id=754452 on 2017-12-11", "class": "Gastropoda", "modified": "2014-02-23T19:08:14Z", "phylum": "Mollusca", "valid_authority": "(Montrouzier, 1861)", "url": "http://www.marinespecies.org/aphia.php?p=taxdetails&id=754452", "unacceptreason": "original combination", "order": "Sacoglossa", "isBrackish": null, "kingdom": "Animalia", "genus": "Lophocercus", "valid_AphiaID": 494417, "lsid": "urn:lsid:marinespecies.org:taxname:754452", "status": "unaccepted", "rank": "Species", "isFreshwater": null, "scientificname": "Lophocercus vigourouxi", "match_type": "exact", "family": "Oxynoidae"}