{"isExtinct": null, "authority": "Gray, 1850", "valid_name": "Tritonia", "isMarine": 1, "isTerrestrial": null, "AphiaID": 742731, "citation": "Gofas, S. (2013). Tritonia (Candiella). In:  MolluscaBase (2017). Accessed through:  World Register of Marine Species at http://www.marinespecies.org/aphia.php?p=taxdetails&id=742731 on 2017-12-11", "class": "Gastropoda", "modified": "2013-10-18T10:24:08Z", "phylum": "Mollusca", "valid_authority": "Cuvier, 1798", "url": "http://www.marinespecies.org/aphia.php?p=taxdetails&id=742731", "unacceptreason": null, "order": "Nudibranchia", "isBrackish": null, "kingdom": "Animalia", "genus": "Tritonia", "valid_AphiaID": 138580, "lsid": "urn:lsid:marinespecies.org:taxname:742731", "status": "unaccepted", "rank": "Subgenus", "isFreshwater": null, "scientificname": "Tritonia (Candiella)", "match_type": "exact", "family": "Tritoniidae"}