{"family": "Cavoliniidae", "url": "http://www.marinespecies.org/aphia.php?p=taxdetails&id=760096", "isBrackish": null, "order": "Thecosomata", "unacceptreason": "misspelling", "isTerrestrial": null, "kingdom": "Animalia", "match_type": "exact", "isMarine": 1, "authority": "(Lesueur, 1821)", "phylum": "Mollusca", "lsid": "urn:lsid:marinespecies.org:taxname:760096", "valid_authority": "(Blainville, 1821)", "status": "unaccepted", "valid_name": "Diacria trispinosa", "genus": "Diacria", "isExtinct": null, "valid_AphiaID": 139045, "class": "Gastropoda", "AphiaID": 760096, "isFreshwater": null, "modified": "2016-10-26T23:30:59Z", "rank": "Species", "citation": "Bouchet, P.; Sartori, Andr\u00e9 F. (2016). Diacria spinosa (Lesueur, 1821). In:  MolluscaBase (2017). Accessed through:  World Register of Marine Species at http://www.marinespecies.org/aphia.php?p=taxdetails&id=760096 on 2017-12-10", "scientificname": "Diacria spinosa"}