{"isExtinct": null, "authority": "Ev. Marcus, 1982", "valid_name": "Boselliidae", "isMarine": 1, "isTerrestrial": null, "AphiaID": 22993, "citation": "Bouchet, P.; Gofas, S. (2011). Boselliidae Ev. Marcus, 1982. In:  MolluscaBase (2017). Accessed through:  World Register of Marine Species at http://www.marinespecies.org/aphia.php?p=taxdetails&id=22993 on 2017-12-10", "class": "Gastropoda", "modified": "2011-04-30T07:08:05Z", "phylum": "Mollusca", "valid_authority": "Ev. Marcus, 1982", "url": "http://www.marinespecies.org/aphia.php?p=taxdetails&id=22993", "unacceptreason": null, "order": "Sacoglossa", "isBrackish": null, "kingdom": "Animalia", "genus": null, "valid_AphiaID": 22993, "lsid": "urn:lsid:marinespecies.org:taxname:22993", "status": "accepted", "rank": "Family", "isFreshwater": null, "scientificname": "Boselliidae", "match_type": "exact", "family": "Boselliidae"}