{"isExtinct": null, "authority": "Urgorri, Cobo & Besteiro, 1991", "valid_name": "Pseudovermis artabrensis", "isMarine": 1, "isTerrestrial": null, "AphiaID": 140881, "citation": "Gofas, S. (2004). Pseudovermis artabrensis Urgorri, Cobo & Besteiro, 1991. In:  MolluscaBase (2017). Accessed through:  World Register of Marine Species at http://www.marinespecies.org/aphia.php?p=taxdetails&id=140881 on 2017-12-11", "class": "Gastropoda", "modified": "2004-12-21T16:54:05Z", "phylum": "Mollusca", "valid_authority": "Urgorri, Cobo & Besteiro, 1991", "url": "http://www.marinespecies.org/aphia.php?p=taxdetails&id=140881", "unacceptreason": null, "order": "Nudibranchia", "isBrackish": null, "kingdom": "Animalia", "genus": "Pseudovermis", "valid_AphiaID": 140881, "lsid": "urn:lsid:marinespecies.org:taxname:140881", "status": "accepted", "rank": "Species", "isFreshwater": null, "scientificname": "Pseudovermis artabrensis", "match_type": "exact", "family": "Pseudovermidae"}