{"valid_AphiaID": 533371, "valid_name": "Pyrunculus rushi", "lsid": "urn:lsid:marinespecies.org:taxname:533371", "match_type": "exact", "rank": "Species", "isFreshwater": null, "valid_authority": "(Dall, 1927)", "kingdom": "Animalia", "class": "Gastropoda", "AphiaID": 533371, "isMarine": 1, "family": "Retusidae", "scientificname": "Pyrunculus rushi", "modified": "2010-10-15T10:54:50Z", "phylum": "Mollusca", "status": "accepted", "unacceptreason": null, "authority": "(Dall, 1927)", "isBrackish": null, "isTerrestrial": null, "order": "Cephalaspidea", "url": "http://www.marinespecies.org/aphia.php?p=taxdetails&id=533371", "genus": "Pyrunculus", "citation": "Rosenberg, G. (2010). Pyrunculus rushi (Dall, 1927). In:  MolluscaBase (2017). Accessed through:  World Register of Marine Species at http://www.marinespecies.org/aphia.php/aphia.php?p=taxdetails&id=533371 on 2017-12-10", "isExtinct": null}