{"isExtinct": null, "authority": "Quatrefages, 1844", "valid_name": "Limapontia senestra", "isMarine": 1, "isTerrestrial": null, "AphiaID": 747478, "citation": "Gofas, S. (2014). Actaeonia senestra Quatrefages, 1844. In:  MolluscaBase (2017). Accessed through:  World Register of Marine Species at http://www.marinespecies.org/aphia.php?p=taxdetails&id=747478 on 2017-12-11", "class": "Gastropoda", "modified": "2014-01-30T13:11:24Z", "phylum": "Mollusca", "valid_authority": "(Quatrefages, 1844)", "url": "http://www.marinespecies.org/aphia.php?p=taxdetails&id=747478", "unacceptreason": "", "order": "Sacoglossa", "isBrackish": null, "kingdom": "Animalia", "genus": "Actaeonia", "valid_AphiaID": 140231, "lsid": "urn:lsid:marinespecies.org:taxname:747478", "status": "unaccepted", "rank": "Species", "isFreshwater": null, "scientificname": "Actaeonia senestra", "match_type": "exact", "family": "Limapontiidae"}