{"isExtinct": null, "authority": "Rankin, 1979", "valid_name": "Microhedyle", "isMarine": null, "isTerrestrial": null, "AphiaID": 556004, "citation": "Bouchet, P. (2010). Livorniella Rankin, 1979. In:  MolluscaBase (2017). Accessed through:  World Register of Marine Species at http://www.marinespecies.org/aphia.php?p=taxdetails&id=556004 on 2017-12-10", "class": "Gastropoda", "modified": "2010-12-17T20:34:47Z", "phylum": "Mollusca", "valid_authority": "Hertling, 1930", "url": "http://www.marinespecies.org/aphia.php?p=taxdetails&id=556004", "unacceptreason": null, "order": "Acochlidiacea", "isBrackish": null, "kingdom": "Animalia", "genus": "Livorniella", "valid_AphiaID": 138176, "lsid": "urn:lsid:marinespecies.org:taxname:556004", "status": "unaccepted", "rank": "Genus", "isFreshwater": null, "scientificname": "Livorniella", "match_type": "exact", "family": "Parhedylidae"}