{"isExtinct": null, "authority": "Risbec, 1937", "valid_name": "Noumeaella curiosa", "isMarine": 1, "isTerrestrial": 0, "AphiaID": 607782, "citation": "Caballer, M.; Bouchet, P. (2013). Noumeaella curiosa Risbec, 1937. In:  MolluscaBase (2017). Accessed through:  World Register of Marine Species at http://marinespecies.org/aphia.php?p=taxdetails&id=607782 on 2017-12-11", "class": "Gastropoda", "modified": "2013-08-15T15:22:37Z", "phylum": "Mollusca", "valid_authority": "Risbec, 1937", "url": "http://www.marinespecies.org/aphia.php?p=taxdetails&id=607782", "unacceptreason": null, "order": "Nudibranchia", "isBrackish": null, "kingdom": "Animalia", "genus": "Noumeaella", "valid_AphiaID": 607782, "lsid": "urn:lsid:marinespecies.org:taxname:607782", "status": "accepted", "rank": "Species", "isFreshwater": 0, "scientificname": "Noumeaella curiosa", "match_type": "exact", "family": "Facelinidae"}