{"family": "Tethydidae", "url": "http://www.marinespecies.org/aphia.php?p=taxdetails&id=577972", "isBrackish": null, "order": "Nudibranchia", "unacceptreason": "original combination", "isTerrestrial": null, "kingdom": "Animalia", "match_type": "exact", "isMarine": 1, "authority": "Allan, 1932", "phylum": "Mollusca", "lsid": "urn:lsid:marinespecies.org:taxname:577972", "valid_authority": "(Allan, 1932)", "status": "unaccepted", "valid_name": "Aplysia extraordinaria", "genus": "Tethys", "isExtinct": null, "valid_AphiaID": 568187, "class": "Gastropoda", "AphiaID": 577972, "isFreshwater": null, "modified": "2011-07-29T12:58:46Z", "rank": "Species", "citation": "Bouchet, P. (2011). Tethys extraordinaria Allan, 1932. In:  MolluscaBase (2017). Accessed through:  World Register of Marine Species at http://www.marinespecies.org/aphia.php?p=taxdetails&id=577972 on 2017-12-10", "scientificname": "Tethys extraordinaria"}