{"isExtinct": null, "authority": "Blainville, 1825", "valid_name": null, "isMarine": 1, "isTerrestrial": null, "AphiaID": 747638, "citation": "Gofas, S. (2017). Aplysia brongniartii Blainville, 1825. In:  MolluscaBase (2017). Accessed through:  World Register of Marine Species at http://www.marinespecies.org/aphia.php?p=taxdetails&id=747638 on 2017-12-10", "class": "Gastropoda", "modified": "2017-04-17T22:40:40Z", "phylum": "Mollusca", "valid_authority": null, "url": "http://www.marinespecies.org/aphia.php?p=taxdetails&id=747638", "unacceptreason": null, "order": "Anaspidea", "isBrackish": null, "kingdom": "Animalia", "genus": "Aplysia", "valid_AphiaID": null, "lsid": "urn:lsid:marinespecies.org:taxname:747638", "status": "nomen dubium", "rank": "Species", "isFreshwater": null, "scientificname": "Aplysia brongniartii", "match_type": "exact", "family": "Aplysiidae"}