{"isExtinct": null, "authority": null, "valid_name": "Fionoidea", "isMarine": 1, "isTerrestrial": null, "AphiaID": 872700, "citation": "Bouchet, P. (2016). Acleioprocta. In:  MolluscaBase (2017). Accessed through:  World Register of Marine Species at http://www.marinespecies.org/aphia.php?p=taxdetails&id=872700 on 2017-12-10", "class": "Gastropoda", "modified": "2016-04-02T13:28:59Z", "phylum": "Mollusca", "valid_authority": "Gray, 1857", "url": "http://www.marinespecies.org/aphia.php?p=taxdetails&id=872700", "unacceptreason": null, "order": "Nudibranchia", "isBrackish": null, "kingdom": "Animalia", "genus": null, "valid_AphiaID": 412646, "lsid": "urn:lsid:marinespecies.org:taxname:872700", "status": "unaccepted", "rank": "Section", "isFreshwater": null, "scientificname": "Acleioprocta", "match_type": "exact", "family": null}