{"isExtinct": null, "authority": "(Garrett, 1879)", "valid_name": "Goniobranchus albopunctatus", "isMarine": 1, "isTerrestrial": 0, "AphiaID": 559920, "citation": "Bouchet, P.; Caballer, M. (2012). Chromodoris albopunctata (Garrett, 1879). In:  MolluscaBase (2017). Accessed through:  World Register of Marine Species at http://www.marinespecies.org/traits/aphia.php?p=taxdetails&id=559920 on 2017-12-11", "class": "Gastropoda", "modified": "2012-04-21T18:29:03Z", "phylum": "Mollusca", "valid_authority": "Garrett, 1879", "url": "http://www.marinespecies.org/aphia.php?p=taxdetails&id=559920", "unacceptreason": null, "order": "Nudibranchia", "isBrackish": null, "kingdom": "Animalia", "genus": "Chromodoris", "valid_AphiaID": 565620, "lsid": "urn:lsid:marinespecies.org:taxname:559920", "status": "unaccepted", "rank": "Species", "isFreshwater": 0, "scientificname": "Chromodoris albopunctata", "match_type": "exact", "family": "Chromodorididae"}