{"family": "Limapontiidae", "url": "http://www.marinespecies.org/aphia.php?p=taxdetails&id=494679", "isBrackish": null, "order": "Sacoglossa", "unacceptreason": null, "isTerrestrial": null, "kingdom": "Animalia", "match_type": "exact", "isMarine": 1, "authority": "K. Jensen, 1990", "phylum": "Mollusca", "lsid": "urn:lsid:marinespecies.org:taxname:494679", "valid_authority": "K. Jensen, 1990", "status": "taxon inquirendum", "valid_name": "Placida daguilarensis", "genus": "Placida", "isExtinct": null, "valid_AphiaID": 494679, "class": "Gastropoda", "AphiaID": 494679, "isFreshwater": null, "modified": "2016-09-12T23:37:52Z", "rank": "Species", "citation": "Bouchet, P. (2016). Placida daguilarensis K. Jensen, 1990. In:  MolluscaBase (2017). Accessed through:  World Register of Marine Species at http://www.marinespecies.org/aphia.php?p=taxdetails&id=494679 on 2017-12-10", "scientificname": "Placida daguilarensis"}