{"isExtinct": null, "authority": "[sic]", "valid_name": "Schizobrachium", "isMarine": null, "isTerrestrial": null, "AphiaID": 818650, "citation": "Rosenberg, G. (2014). Schizobranchium [sic]. In:  MolluscaBase (2017). Accessed through:  World Register of Marine Species at http://www.marinespecies.org/aphia.php?p=taxdetails&id=818650 on 2017-12-10", "class": "Gastropoda", "modified": "2014-10-02T19:40:31Z", "phylum": "Mollusca", "valid_authority": "Meisenheimer, 1903", "url": "http://www.marinespecies.org/aphia.php?p=taxdetails&id=818650", "unacceptreason": "misspelling", "order": "Gymnosomata", "isBrackish": null, "kingdom": "Animalia", "genus": "Schizobranchium", "valid_AphiaID": 414993, "lsid": "urn:lsid:marinespecies.org:taxname:818650", "status": "unaccepted", "rank": "Genus", "isFreshwater": null, "scientificname": "Schizobranchium", "match_type": "exact", "family": "Pneumodermatidae"}