{"valid_AphiaID": 140075, "valid_name": "Haminoea navicula", "lsid": "urn:lsid:marinespecies.org:taxname:153323", "match_type": "exact", "rank": "Species", "isFreshwater": 0, "valid_authority": "(da Costa, 1778)", "kingdom": "Animalia", "class": "Gastropoda", "AphiaID": 153323, "isMarine": 1, "family": "Haminoeidae", "scientificname": "Haminoea cornea", "modified": "2015-05-22T18:30:37Z", "phylum": "Mollusca", "status": "unaccepted", "unacceptreason": "synonym", "authority": "(Lamarck, 1822)", "isBrackish": null, "isTerrestrial": 0, "order": "Cephalaspidea", "url": "http://www.marinespecies.org/aphia.php?p=taxdetails&id=153323", "genus": "Haminoea", "citation": "Bouchet, P. (2015). Haminoea cornea (Lamarck, 1822). In:  MolluscaBase (2017). Accessed through:  World Register of Marine Species at http://www.marinespecies.org/aphia.php?p=taxdetails&id=153323 on 2017-12-10", "isExtinct": null}