{"family": "Arminidae", "url": "http://www.marinespecies.org/aphia.php?p=taxdetails&id=138809", "isBrackish": null, "order": "Nudibranchia", "unacceptreason": "declared <i>nomen oblitum</i> by Jensen & Nielsen (2014)", "isTerrestrial": null, "kingdom": "Animalia", "match_type": "exact", "isMarine": 1, "authority": "Blainville, 1823", "phylum": "Mollusca", "lsid": "urn:lsid:marinespecies.org:taxname:138809", "valid_authority": "(Bergh, 1861)", "status": "unaccepted", "valid_name": "Armina quadrilateralis", "genus": "Linguella", "isExtinct": null, "valid_AphiaID": 754928, "class": "Gastropoda", "AphiaID": 138809, "isFreshwater": null, "modified": "2014-03-04T19:55:11Z", "rank": "Species", "citation": "Bouchet, P.; Gofas, S. (2014). Linguella elfortiana Blainville, 1823. In:  MolluscaBase (2017). Accessed through:  World Register of Marine Species at http://www.marinespecies.org/traits/aphia.php?p=taxdetails&id=138809 on 2017-12-10", "scientificname": "Linguella elfortiana"}