{"family": "Hermaeidae", "url": "http://www.marinespecies.org/aphia.php?p=taxdetails&id=568088", "isBrackish": null, "order": "Sacoglossa", "unacceptreason": "uncertain synonym", "isTerrestrial": null, "kingdom": "Animalia", "match_type": "exact", "isMarine": 1, "authority": "A. Costa, 1864", "phylum": "Mollusca", "lsid": "urn:lsid:marinespecies.org:taxname:568088", "valid_authority": "(Montagu, 1816)", "status": "unaccepted", "valid_name": "Hermaea bifida", "genus": "Physopneumon", "isExtinct": null, "valid_AphiaID": 140092, "class": "Gastropoda", "AphiaID": 568088, "isFreshwater": null, "modified": "2017-04-21T23:01:44Z", "rank": "Species", "citation": "Gofas, S.; Bouchet, P. (2017). Physopneumon carneum A. Costa, 1864. In:  MolluscaBase (2017). Accessed through:  World Register of Marine Species at http://www.marinespecies.org/aphia.php?p=taxdetails&id=568088 on 2017-12-10", "scientificname": "Physopneumon carneum"}