{"valid_AphiaID": 819290, "valid_name": "Retusa crispula", "lsid": "urn:lsid:marinespecies.org:taxname:761117", "match_type": "exact", "rank": "Species", "isFreshwater": null, "valid_authority": "(Watson, 1883)", "kingdom": "Animalia", "class": "Gastropoda", "AphiaID": 761117, "isMarine": 1, "family": "Cylichnidae", "scientificname": "Cylichna crispula", "modified": "2014-10-11T10:41:55Z", "phylum": "Mollusca", "status": "unaccepted", "unacceptreason": "original combination", "authority": "Watson, 1883", "isBrackish": null, "isTerrestrial": null, "order": "Cephalaspidea", "url": "http://www.marinespecies.org/aphia.php?p=taxdetails&id=761117", "genus": "Cylichna", "citation": "Bouchet, P.; Sartori, Andr\u00e9 F. (2014). Cylichna crispula Watson, 1883. In:  MolluscaBase (2017). Accessed through:  World Register of Marine Species at http://www.marinespecies.org/aphia.php?p=taxdetails&id=761117 on 2017-12-10", "isExtinct": null}