{"isExtinct": null, "authority": "Baba, 1955", "valid_name": "Catriona nigricolora", "isMarine": 1, "isTerrestrial": null, "AphiaID": 850656, "citation": "Bouchet, P. (2015). Cratena nigricolora Baba, 1955. In:  MolluscaBase (2017). Accessed through:  World Register of Marine Species at http://www.marinespecies.org/aphia.php?p=taxdetails&id=850656 on 2017-12-11", "class": "Gastropoda", "modified": "2015-07-06T10:10:28Z", "phylum": "Mollusca", "valid_authority": "(Baba, 1955)", "url": "http://www.marinespecies.org/aphia.php?p=taxdetails&id=850656", "unacceptreason": "original combination", "order": "Nudibranchia", "isBrackish": null, "kingdom": "Animalia", "genus": "Cratena", "valid_AphiaID": 850655, "lsid": "urn:lsid:marinespecies.org:taxname:850656", "status": "unaccepted", "rank": "Species", "isFreshwater": null, "scientificname": "Cratena nigricolora", "match_type": "exact", "family": "Facelinidae"}