{"family": "Onchidorididae", "url": "http://www.marinespecies.org/aphia.php?p=taxdetails&id=140634", "isBrackish": null, "order": "Nudibranchia", "unacceptreason": null, "isTerrestrial": 0, "kingdom": "Animalia", "match_type": "exact", "isMarine": 1, "authority": "(Alder & Hancock, 1842)", "phylum": "Mollusca", "lsid": "urn:lsid:marinespecies.org:taxname:140634", "valid_authority": "(O. F. M\u00fcller, 1776)", "status": "unaccepted", "valid_name": "Onchidoris muricata", "genus": "Onchidoris", "isExtinct": null, "valid_AphiaID": 140640, "class": "Gastropoda", "AphiaID": 140634, "isFreshwater": 0, "modified": "2013-09-11T16:49:34Z", "rank": "Species", "citation": "Caballer, M.; Gofas, S. (2013). Onchidoris aspera (Alder & Hancock, 1842). In:  MolluscaBase (2017). Accessed through:  World Register of Marine Species at http://www.marinespecies.org/aphia.php?p=taxdetails&id=140634 on 2017-12-10", "scientificname": "Onchidoris aspera"}