{"isExtinct": null, "authority": "(Vicente, 1975)", "valid_name": "Paraflabellina gabinierei", "isMarine": 1, "isTerrestrial": null, "AphiaID": 1048139, "citation": "Picton, B. (2017). Paraflabellina gabinierei. In:  MolluscaBase (2017). Accessed through:  World Register of Marine Species at http://www.marinespecies.org/aphia.php?p=taxdetails&id=1048139 on 2017-12-11", "class": "Gastropoda", "modified": "2017-12-09T18:28:41Z", "phylum": "Mollusca", "valid_authority": "(Vicente, 1975)", "url": "http://www.marinespecies.org/aphia.php?p=taxdetails&id=1048139", "unacceptreason": null, "order": "Nudibranchia", "isBrackish": null, "kingdom": "Animalia", "genus": "Paraflabellina", "valid_AphiaID": 1048139, "lsid": "urn:lsid:marinespecies.org:taxname:1048139", "status": "accepted", "rank": "Species", "isFreshwater": null, "scientificname": "Paraflabellina gabinierei", "match_type": "exact", "family": "Flabellinidae"}