{"isExtinct": null, "authority": "Fischer P. in de Folin, 1869", "valid_name": "Cylichnina robagliana", "isMarine": 1, "isTerrestrial": null, "AphiaID": 747919, "citation": "Gofas, S. (2014). Bulla robagliana Fischer P. in de Folin, 1869. In:  MolluscaBase (2017). Accessed through:  World Register of Marine Species at http://www.marinespecies.org/traits/aphia.php?p=taxdetails&id=747919 on 2017-12-10", "class": "Gastropoda", "modified": "2014-01-30T13:11:24Z", "phylum": "Mollusca", "valid_authority": "(P. Fischer, 1869)", "url": "http://www.marinespecies.org/aphia.php?p=taxdetails&id=747919", "unacceptreason": "", "order": "Cephalaspidea", "isBrackish": null, "kingdom": "Animalia", "genus": "Bulla", "valid_AphiaID": 141121, "lsid": "urn:lsid:marinespecies.org:taxname:747919", "status": "unaccepted", "rank": "Species", "isFreshwater": null, "scientificname": "Bulla robagliana", "match_type": "exact", "family": "Bullidae"}