{"valid_AphiaID": 138461, "valid_name": "Rostanga", "lsid": "urn:lsid:marinespecies.org:taxname:738239", "match_type": "exact", "rank": "Genus", "isFreshwater": null, "valid_authority": "Bergh, 1879", "kingdom": "Animalia", "class": "Gastropoda", "AphiaID": 738239, "isMarine": 1, "family": "Dorididae", "scientificname": "Rhabdochila", "modified": "2013-08-26T19:24:55Z", "phylum": "Mollusca", "status": "unaccepted", "unacceptreason": "objective synonym of <i>Rostanga</i>", "authority": "P. Fischer, 1883", "isBrackish": null, "isTerrestrial": null, "order": "Nudibranchia", "url": "http://www.marinespecies.org/aphia.php?p=taxdetails&id=738239", "genus": "Rhabdochila", "citation": "Bouchet, P. (2013). Rhabdochila P. Fischer, 1883. In:  MolluscaBase (2017). Accessed through:  World Register of Marine Species at http://marinespecies.org/aphia.php?p=taxdetails&id=738239 on 2017-12-10", "isExtinct": null}