{"isExtinct": null, "authority": "Pease, 1860", "valid_name": "Melibe pilosa", "isMarine": 1, "isTerrestrial": 0, "AphiaID": 221064, "citation": "Caballer, M.; Rosenberg, G. (2013). Melibe pilosa Pease, 1860. In:  MolluscaBase (2017). Accessed through:  World Register of Marine Species at http://www.marinespecies.org/aphia.php?p=taxdetails&id=221064 on 2017-12-11", "class": "Gastropoda", "modified": "2013-08-07T16:58:23Z", "phylum": "Mollusca", "valid_authority": "Pease, 1860", "url": "http://www.marinespecies.org/aphia.php?p=taxdetails&id=221064", "unacceptreason": null, "order": "Nudibranchia", "isBrackish": null, "kingdom": "Animalia", "genus": "Melibe", "valid_AphiaID": 221064, "lsid": "urn:lsid:marinespecies.org:taxname:221064", "status": "accepted", "rank": "Species", "isFreshwater": 0, "scientificname": "Melibe pilosa", "match_type": "exact", "family": "Tethydidae"}