{"family": "Juliidae", "url": "http://www.marinespecies.org/aphia.php?p=taxdetails&id=492585", "isBrackish": null, "order": "Sacoglossa", "unacceptreason": null, "isTerrestrial": null, "kingdom": "Animalia", "match_type": "exact", "isMarine": 1, "authority": "Kawaguchi, 1981", "phylum": "Mollusca", "lsid": "urn:lsid:marinespecies.org:taxname:492585", "valid_authority": "Kawaguchi, 1981", "status": "accepted", "valid_name": "Julia zebra", "genus": "Julia", "isExtinct": null, "valid_AphiaID": 492585, "class": "Gastropoda", "AphiaID": 492585, "isFreshwater": null, "modified": "2012-04-09T18:22:58Z", "rank": "Species", "citation": "Bouchet, P. (2012). Julia zebra Kawaguchi, 1981. In:  MolluscaBase (2017). Accessed through:  World Register of Marine Species at http://www.marinespecies.org/aphia.php?p=taxdetails&id=492585 on 2017-12-10", "scientificname": "Julia zebra"}