{"isExtinct": null, "authority": "Crosse in Angas, 1864", "valid_name": "Thordisa verrucosa", "isMarine": 1, "isTerrestrial": 0, "AphiaID": 533997, "citation": "Caballer, M.; Bouchet, P. (2013). Goniodoris verrucosa Crosse in Angas, 1864. In:  MolluscaBase (2017). Accessed through:  World Register of Marine Species at http://www.marinespecies.org/aphia.php?p=taxdetails&id=533997 on 2017-12-11", "class": "Gastropoda", "modified": "2013-10-17T14:47:34Z", "phylum": "Mollusca", "valid_authority": "(Crosse in Angas, 1864)", "url": "http://www.marinespecies.org/aphia.php?p=taxdetails&id=533997", "unacceptreason": "original combination", "order": "Nudibranchia", "isBrackish": null, "kingdom": "Animalia", "genus": "Goniodoris", "valid_AphiaID": 533996, "lsid": "urn:lsid:marinespecies.org:taxname:533997", "status": "unaccepted", "rank": "Species", "isFreshwater": 0, "scientificname": "Goniodoris verrucosa", "match_type": "exact", "family": "Goniodorididae"}