{"family": "Chromodorididae", "url": "http://www.marinespecies.org/aphia.php?p=taxdetails&id=558618", "isBrackish": null, "order": "Nudibranchia", "unacceptreason": null, "isTerrestrial": 0, "kingdom": "Animalia", "match_type": "exact", "isMarine": 1, "authority": "Semper <i>in</i> Bergh, 1876", "phylum": "Mollusca", "lsid": "urn:lsid:marinespecies.org:taxname:558618", "valid_authority": "Semper <i>in</i> Bergh, 1876", "status": "accepted", "valid_name": "Ceratosoma gracillimum", "genus": "Ceratosoma", "isExtinct": null, "valid_AphiaID": 558618, "class": "Gastropoda", "AphiaID": 558618, "isFreshwater": 0, "modified": "2011-02-21T09:54:00Z", "rank": "Species", "citation": "Caballer, M. (2011). Ceratosoma gracillimum Semper in Bergh, 1876. In:  MolluscaBase (2017). Accessed through:  World Register of Marine Species at http://www.marinespecies.org/aphia.php?p=taxdetails&id=558618 on 2017-12-10", "scientificname": "Ceratosoma gracillimum"}