{"isExtinct": 1, "authority": "Audenino, 1899", "valid_name": "Clio triplicata", "isMarine": 1, "isTerrestrial": null, "AphiaID": 932971, "citation": "Marshall, B. (2017). Clio triplicata Audenino, 1899&nbsp;&#8224;. In:  MolluscaBase (2017). Accessed through:  World Register of Marine Species at http://www.marinespecies.org/aphia.php?p=taxdetails&id=932971 on 2017-12-11", "class": "Gastropoda", "modified": "2017-01-04T06:56:31Z", "phylum": "Mollusca", "valid_authority": "Audenino, 1899", "url": "http://www.marinespecies.org/aphia.php?p=taxdetails&id=932971", "unacceptreason": null, "order": "Thecosomata", "isBrackish": null, "kingdom": "Animalia", "genus": "Clio", "valid_AphiaID": 932971, "lsid": "urn:lsid:marinespecies.org:taxname:932971", "status": "accepted", "rank": "Species", "isFreshwater": null, "scientificname": "Clio triplicata", "match_type": "exact", "family": "Cliidae"}