{"family": "Discodorididae", "url": "http://www.marinespecies.org/aphia.php?p=taxdetails&id=457015", "isBrackish": null, "order": "Nudibranchia", "unacceptreason": null, "isTerrestrial": null, "kingdom": "Animalia", "match_type": "exact", "isMarine": 1, "authority": "Carlson & Hoff, 2000", "phylum": "Mollusca", "lsid": "urn:lsid:marinespecies.org:taxname:457015", "valid_authority": "Carlson & Hoff, 2000", "status": "accepted", "valid_name": "Halgerda johnsonorum", "genus": "Halgerda", "isExtinct": null, "valid_AphiaID": 457015, "class": "Gastropoda", "AphiaID": 457015, "isFreshwater": null, "modified": "2016-03-20T05:03:15Z", "rank": "Species", "citation": "Bouchet, P. (2016). Halgerda johnsonorum Carlson & Hoff, 2000. In:  MolluscaBase (2017). Accessed through:  World Register of Marine Species at http://www.marinespecies.org/aphia.php/aphia.php?p=taxdetails&id=457015 on 2017-12-10", "scientificname": "Halgerda johnsonorum"}