{"isExtinct": null, "authority": "B\u00e9, MacClintock & Currie, 1972", "valid_name": "Cuvierina atlantica", "isMarine": 1, "isTerrestrial": null, "AphiaID": 246649, "citation": "Gofas, S. (2017). Cuvierina atlantica B\u00e9, MacClintock & Currie, 1972. In:  MolluscaBase (2017). Accessed through:  World Register of Marine Species at http://www.marinespecies.org/aphia.php?p=taxdetails&id=246649 on 2017-12-11", "class": "Gastropoda", "modified": "2007-10-08T22:02:47Z", "phylum": "Mollusca", "valid_authority": "B\u00e9, MacClintock & Currie, 1972", "url": "http://www.marinespecies.org/aphia.php?p=taxdetails&id=246649", "unacceptreason": null, "order": "Thecosomata", "isBrackish": null, "kingdom": "Animalia", "genus": "Cuvierina", "valid_AphiaID": 246649, "lsid": "urn:lsid:marinespecies.org:taxname:246649", "status": "accepted", "rank": "Species", "isFreshwater": null, "scientificname": "Cuvierina atlantica", "match_type": "exact", "family": "Cuvierinidae"}