{"isExtinct": null, "authority": "Agassiz, 1847", "valid_name": "Pneumoderma", "isMarine": 1, "isTerrestrial": null, "AphiaID": 719614, "citation": "Bouchet, P. (2013). Pneumonoderma Agassiz, 1847. In:  MolluscaBase (2017). Accessed through:  World Register of Marine Species at http://www.marinespecies.org/traits/aphia.php?p=taxdetails&id=719614 on 2017-12-10", "class": "Gastropoda", "modified": "2013-02-20T18:44:59Z", "phylum": "Mollusca", "valid_authority": "de Roissy, 1805", "url": "http://www.marinespecies.org/aphia.php?p=taxdetails&id=719614", "unacceptreason": "unjustified emendation", "order": "Gymnosomata", "isBrackish": null, "kingdom": "Animalia", "genus": "Pneumonoderma", "valid_AphiaID": 138365, "lsid": "urn:lsid:marinespecies.org:taxname:719614", "status": "unaccepted", "rank": "Genus", "isFreshwater": null, "scientificname": "Pneumonoderma", "match_type": "exact", "family": "Pneumodermatidae"}