{"family": "Chromodorididae", "url": "http://www.marinespecies.org/aphia.php?p=taxdetails&id=597357", "isBrackish": null, "order": "Nudibranchia", "unacceptreason": null, "isTerrestrial": null, "kingdom": "Animalia", "match_type": "exact", "isMarine": 1, "authority": "(Rudman & S. Johnson, 1985)", "phylum": "Mollusca", "lsid": "urn:lsid:marinespecies.org:taxname:597357", "valid_authority": "(Rudman & S. Johnson, 1985)", "status": "accepted", "valid_name": "Goniobranchus galactos", "genus": "Goniobranchus", "isExtinct": null, "valid_AphiaID": 597357, "class": "Gastropoda", "AphiaID": 597357, "isFreshwater": null, "modified": "2012-04-21T18:29:03Z", "rank": "Species", "citation": "Bouchet, P. (2012). Goniobranchus galactos (Rudman & S. Johnson, 1985). In:  MolluscaBase (2017). Accessed through:  World Register of Marine Species at http://www.marinespecies.org/aphia.php?p=taxdetails&id=597357 on 2017-12-10", "scientificname": "Goniobranchus galactos"}