{"family": "Cavoliniidae", "url": "http://www.marinespecies.org/aphia.php?p=taxdetails&id=390586", "isBrackish": null, "order": "Thecosomata", "unacceptreason": null, "isTerrestrial": null, "kingdom": "Animalia", "match_type": "exact", "isMarine": 1, "authority": "Rampal, 2002", "phylum": "Mollusca", "lsid": "urn:lsid:marinespecies.org:taxname:390586", "valid_authority": "Rampal, 2002", "status": "accepted", "valid_name": "Cavolinia labiata robusta", "genus": "Cavolinia", "isExtinct": 1, "valid_AphiaID": 390586, "class": "Gastropoda", "AphiaID": 390586, "isFreshwater": null, "modified": "2013-02-11T15:46:50Z", "rank": "Subspecies", "citation": "Bouchet, P. (2013). Cavolinia labiata robusta. In:  MolluscaBase (2017). Accessed through:  World Register of Marine Species at http://www.marinespecies.org/aphia.php?p=taxdetails&id=390586 on 2017-12-10", "scientificname": "Cavolinia labiata robusta"}