{"valid_AphiaID": 599201, "valid_name": "Volvulella nesentus", "lsid": "urn:lsid:marinespecies.org:taxname:765232", "match_type": "exact", "rank": "Species", "isFreshwater": null, "valid_authority": "(Finlay, 1926)", "kingdom": "Animalia", "class": "Gastropoda", "AphiaID": 765232, "isMarine": 1, "family": "Rhizoridae", "scientificname": "Volvulella reflexa", "modified": "2016-07-17T21:28:33Z", "phylum": "Mollusca", "status": "unaccepted", "unacceptreason": "not Hutton, 1885", "authority": "sensu Suter, 1913", "isBrackish": null, "isTerrestrial": null, "order": "Cephalaspidea", "url": "http://www.marinespecies.org/aphia.php?p=taxdetails&id=765232", "genus": "Volvulella", "citation": "Marshall, B.; Rosenberg, G. (2016). Volvulella reflexa sensu Suter, 1913. In:  MolluscaBase (2017). Accessed through:  World Register of Marine Species at http://www.marinespecies.org/aphia.php?p=taxdetails&id=765232 on 2017-12-10", "isExtinct": null}