{"valid_AphiaID": 412598, "valid_name": "Bornellidae", "lsid": "urn:lsid:marinespecies.org:taxname:412598", "match_type": "exact", "rank": "Family", "isFreshwater": null, "valid_authority": "Bergh, 1874", "kingdom": "Animalia", "class": "Gastropoda", "AphiaID": 412598, "isMarine": 1, "family": "Bornellidae", "scientificname": "Bornellidae", "modified": "2017-10-31T00:19:27Z", "phylum": "Mollusca", "status": "accepted", "unacceptreason": null, "authority": "Bergh, 1874", "isBrackish": null, "isTerrestrial": null, "order": "Nudibranchia", "url": "http://www.marinespecies.org/aphia.php?p=taxdetails&id=412598", "genus": null, "citation": "Picton, B.; Bouchet, P. (2017). Bornellidae Bergh, 1874. In:  MolluscaBase (2017). Accessed through:  World Register of Marine Species at http://www.marinespecies.org/aphia.php?p=taxdetails&id=412598 on 2017-12-10", "isExtinct": null}