{"valid_AphiaID": 555992, "valid_name": "Pseudunela cornuta", "lsid": "urn:lsid:marinespecies.org:taxname:555992", "match_type": "exact", "rank": "Species", "isFreshwater": null, "valid_authority": "(Challis, 1970)", "kingdom": "Animalia", "class": "Gastropoda", "AphiaID": 555992, "isMarine": 1, "family": "Pseudunelidae", "scientificname": "Pseudunela cornuta", "modified": "2010-12-17T20:34:47Z", "phylum": "Mollusca", "status": "accepted", "unacceptreason": null, "authority": "(Challis, 1970)", "isBrackish": null, "isTerrestrial": null, "order": "Acochlidiacea", "url": "http://www.marinespecies.org/aphia.php?p=taxdetails&id=555992", "genus": "Pseudunela", "citation": "Bouchet, P. (2010). Pseudunela cornuta (Challis, 1970). In:  MolluscaBase (2017). Accessed through:  World Register of Marine Species at http://www.marinespecies.org/aphia.php?p=taxdetails&id=555992 on 2017-12-10", "isExtinct": null}