{"valid_AphiaID": 742262, "valid_name": "Fucola", "lsid": "urn:lsid:marinespecies.org:taxname:742262", "match_type": "exact", "rank": "Genus", "isFreshwater": null, "valid_authority": "Quoy & Gaimard, 1833", "kingdom": "Animalia", "class": "Gastropoda", "AphiaID": 742262, "isMarine": 1, "family": "Gymnodorididae", "scientificname": "Fucola", "modified": "2013-10-07T11:20:56Z", "phylum": "Mollusca", "status": "taxon inquirendum", "unacceptreason": null, "authority": "Quoy & Gaimard, 1833", "isBrackish": null, "isTerrestrial": null, "order": "Nudibranchia", "url": "http://www.marinespecies.org/aphia.php?p=taxdetails&id=742262", "genus": "Fucola", "citation": "Gofas, S. (2017). Fucola Quoy & Gaimard, 1833. In:  MolluscaBase (2017). Accessed through:  World Register of Marine Species at http://www.marinespecies.org/aphia.php?p=taxdetails&id=742262 on 2017-12-10", "isExtinct": null}