{"isExtinct": null, "authority": "Ortea, Moro & Bacallado, 2016", "valid_name": "Quijotidae", "isMarine": 1, "isTerrestrial": null, "AphiaID": 932596, "citation": "Bouchet, P. (2017). Quijotidae Ortea, Moro & Bacallado, 2016. In:  MolluscaBase (2017). Accessed through:  World Register of Marine Species at http://www.marinespecies.org/aphia.php?p=taxdetails&id=932596 on 2017-12-10", "class": "Gastropoda", "modified": "2017-01-01T18:49:17Z", "phylum": "Mollusca", "valid_authority": "Ortea, Moro & Bacallado, 2016", "url": "http://www.marinespecies.org/aphia.php?p=taxdetails&id=932596", "unacceptreason": null, "order": "Pleurobranchomorpha", "isBrackish": null, "kingdom": "Animalia", "genus": null, "valid_AphiaID": 932596, "lsid": "urn:lsid:marinespecies.org:taxname:932596", "status": "accepted", "rank": "Family", "isFreshwater": null, "scientificname": "Quijotidae", "match_type": "exact", "family": "Quijotidae"}