{"isExtinct": null, "authority": "Bergh, 1874", "valid_name": "Jorunna rubescens", "isMarine": 1, "isTerrestrial": null, "AphiaID": 534390, "citation": "Bouchet, P. (2010). Kentrodoris rubescens Bergh, 1874. In:  MolluscaBase (2017). Accessed through:  World Register of Marine Species at http://www.marinespecies.org/aphia.php?p=taxdetails&id=534390 on 2017-12-11", "class": "Gastropoda", "modified": "2010-10-18T17:29:19Z", "phylum": "Mollusca", "valid_authority": "(Bergh, 1876)", "url": "http://www.marinespecies.org/aphia.php?p=taxdetails&id=534390", "unacceptreason": "original combination", "order": "Nudibranchia", "isBrackish": null, "kingdom": "Animalia", "genus": "Kentrodoris", "valid_AphiaID": 534389, "lsid": "urn:lsid:marinespecies.org:taxname:534390", "status": "unaccepted", "rank": "Species", "isFreshwater": null, "scientificname": "Kentrodoris rubescens", "match_type": "exact", "family": "Discodorididae"}