{"isExtinct": null, "authority": "Sordi, 1980", "valid_name": "Chelidonura africana", "isMarine": 1, "isTerrestrial": null, "AphiaID": 138730, "citation": "Gofas, S. (2017). Chelidonura italica Sordi, 1980. In:  MolluscaBase (2017). Accessed through:  World Register of Marine Species at http://www.marinespecies.org/aphia.php?p=taxdetails&id=138730 on 2017-12-10", "class": "Gastropoda", "modified": "2005-09-09T12:04:58Z", "phylum": "Mollusca", "valid_authority": "Pruvot-Fol, 1953", "url": "http://www.marinespecies.org/aphia.php?p=taxdetails&id=138730", "unacceptreason": "synonym", "order": "Cephalaspidea", "isBrackish": null, "kingdom": "Animalia", "genus": "Chelidonura", "valid_AphiaID": 181203, "lsid": "urn:lsid:marinespecies.org:taxname:138730", "status": "unaccepted", "rank": "Species", "isFreshwater": null, "scientificname": "Chelidonura italica", "match_type": "exact", "family": "Aglajidae"}