{"isExtinct": null, "authority": "(O'Donoghue, 1929)", "valid_name": "Pleurobranchus sculptatus", "isMarine": 1, "isTerrestrial": null, "AphiaID": 765106, "citation": "Sartori, Andr\u00e9 F. (2014). Pleurobranchus sculptatus (O'Donoghue, 1929). In:  MolluscaBase (2017). Accessed through:  World Register of Marine Species at http://www.marinespecies.org/aphia.php?p=taxdetails&id=765106 on 2017-12-10", "class": "Gastropoda", "modified": "2014-06-10T10:36:17Z", "phylum": "Mollusca", "valid_authority": "(O'Donoghue, 1929)", "url": "http://www.marinespecies.org/aphia.php?p=taxdetails&id=765106", "unacceptreason": null, "order": "Pleurobranchomorpha", "isBrackish": null, "kingdom": "Animalia", "genus": "Pleurobranchus", "valid_AphiaID": 765106, "lsid": "urn:lsid:marinespecies.org:taxname:765106", "status": "taxon inquirendum", "rank": "Species", "isFreshwater": null, "scientificname": "Pleurobranchus sculptatus", "match_type": "exact", "family": "Pleurobranchidae"}