{"isExtinct": null, "authority": "Leach, 1852", "valid_name": "Aplysia punctata", "isMarine": 1, "isTerrestrial": null, "AphiaID": 747644, "citation": "Gofas, S. (2014). Aplysia griffithsiana Leach, 1852. In:  MolluscaBase (2017). Accessed through:  World Register of Marine Species at http://www.marinespecies.org/aphia.php?p=taxdetails&id=747644 on 2017-12-10", "class": "Gastropoda", "modified": "2014-01-30T13:11:24Z", "phylum": "Mollusca", "valid_authority": "(Cuvier, 1803)", "url": "http://www.marinespecies.org/aphia.php?p=taxdetails&id=747644", "unacceptreason": "dubious synonym", "order": "Anaspidea", "isBrackish": null, "kingdom": "Animalia", "genus": "Aplysia", "valid_AphiaID": 138758, "lsid": "urn:lsid:marinespecies.org:taxname:747644", "status": "unaccepted", "rank": "Species", "isFreshwater": null, "scientificname": "Aplysia griffithsiana", "match_type": "exact", "family": "Aplysiidae"}