{"isExtinct": null, "authority": "(Cockerell, 1901)", "valid_name": "Felimare porterae", "isMarine": 1, "isTerrestrial": 0, "AphiaID": 558668, "citation": "Bouchet, P.; Caballer, M. (2012). Mexichromis porterae (Cockerell, 1901). In:  MolluscaBase (2017). Accessed through:  World Register of Marine Species at http://www.marinespecies.org/aphia.php?p=taxdetails&id=558668 on 2017-12-11", "class": "Gastropoda", "modified": "2012-04-26T21:11:25Z", "phylum": "Mollusca", "valid_authority": "(Cockerell, 1901)", "url": "http://www.marinespecies.org/aphia.php?p=taxdetails&id=558668", "unacceptreason": null, "order": "Nudibranchia", "isBrackish": null, "kingdom": "Animalia", "genus": "Mexichromis", "valid_AphiaID": 597534, "lsid": "urn:lsid:marinespecies.org:taxname:558668", "status": "unaccepted", "rank": "Species", "isFreshwater": 0, "scientificname": "Mexichromis porterae", "match_type": "exact", "family": "Chromodorididae"}