{"valid_AphiaID": 761112, "valid_name": "Cylichna tubulosa", "lsid": "urn:lsid:marinespecies.org:taxname:761112", "match_type": "exact", "rank": "Species", "isFreshwater": null, "valid_authority": "Gould, 1859", "kingdom": "Animalia", "class": "Gastropoda", "AphiaID": 761112, "isMarine": 1, "family": "Cylichnidae", "scientificname": "Cylichna tubulosa", "modified": "2014-05-05T11:37:39Z", "phylum": "Mollusca", "status": "accepted", "unacceptreason": null, "authority": "Gould, 1859", "isBrackish": null, "isTerrestrial": null, "order": "Cephalaspidea", "url": "http://www.marinespecies.org/aphia.php?p=taxdetails&id=761112", "genus": "Cylichna", "citation": "Sartori, Andr\u00e9 F. (2014). Cylichna tubulosa Gould, 1859. In:  MolluscaBase (2017). Accessed through:  World Register of Marine Species at http://www.marinespecies.org/aphia.php?p=taxdetails&id=761112 on 2017-12-10", "isExtinct": null}