{"isExtinct": null, "authority": "Ev. Marcus, 1984", "valid_name": "Berthella tamiu", "isMarine": 1, "isTerrestrial": null, "AphiaID": 532445, "citation": "Rosenberg, G. (2010). Berthella tamiu Ev. Marcus, 1984. In:  MolluscaBase (2017). Accessed through:  World Register of Marine Species at http://www.marinespecies.org/aphia.php?p=taxdetails&id=532445 on 2017-12-10", "class": "Gastropoda", "modified": "2010-10-15T10:54:50Z", "phylum": "Mollusca", "valid_authority": "Ev. Marcus, 1984", "url": "http://www.marinespecies.org/aphia.php?p=taxdetails&id=532445", "unacceptreason": null, "order": "Pleurobranchomorpha", "isBrackish": null, "kingdom": "Animalia", "genus": "Berthella", "valid_AphiaID": 532445, "lsid": "urn:lsid:marinespecies.org:taxname:532445", "status": "accepted", "rank": "Species", "isFreshwater": null, "scientificname": "Berthella tamiu", "match_type": "exact", "family": "Pleurobranchidae"}