{"family": "Polyceridae", "url": "http://www.marinespecies.org/aphia.php?p=taxdetails&id=224331", "isBrackish": null, "order": "Nudibranchia", "unacceptreason": null, "isTerrestrial": null, "kingdom": "Animalia", "match_type": "exact", "isMarine": 1, "authority": "Ortea, 1989", "phylum": "Mollusca", "lsid": "urn:lsid:marinespecies.org:taxname:224331", "valid_authority": "Ortea, 1989", "status": "accepted", "valid_name": "Tambja anayana", "genus": "Tambja", "isExtinct": null, "valid_AphiaID": 224331, "class": "Gastropoda", "AphiaID": 224331, "isFreshwater": null, "modified": "2010-10-11T20:50:43Z", "rank": "Species", "citation": "Bouchet, P. (2010). Tambja anayana Ortea, 1989. In:  MolluscaBase (2017). Accessed through:  World Register of Marine Species at http://marinespecies.org/aphia.php/aphia.php?p=taxdetails&id=224331 on 2017-12-10", "scientificname": "Tambja anayana"}